pipsalabim/__init__.py
pipsalabim/cli.py
pipsalabim/api/__init__.py
pipsalabim/api/report.py
pipsalabim/api/update.py
pipsalabim/core/__init__.py
pipsalabim/core/imports.py
pipsalabim/core/logger.py
pipsalabim/core/utils.py
pipsalabim-0.2.0.dist-info/AUTHORS.rst
pipsalabim-0.2.0.dist-info/LICENSE
pipsalabim-0.2.0.dist-info/METADATA
pipsalabim-0.2.0.dist-info/WHEEL
pipsalabim-0.2.0.dist-info/entry_points.txt
pipsalabim-0.2.0.dist-info/top_level.txt
pipsalabim-0.2.0.dist-info/RECORD
