Metadata-Version: 2.1
Name: pipsalabim
Version: 0.2.0
Summary: Pip Sala Bim is an assistant to guess your pip dependencies from your code, without using a requirements file.
Home-page: https://github.com/LuisAlejandro/pipsalabim
Author: Luis Alejandro Martínez Faneyth
Author-email: luis@collagelabs.org
License: GNU GENERAL PUBLIC LICENSE
Keywords: pip,requirements.txt,guess,report
Platform: posix
Platform: linux
Classifier: Development Status :: 5 - Production/Stable
Classifier: Intended Audience :: Developers
Classifier: License :: OSI Approved :: GNU General Public License v3 (GPLv3)
Classifier: Natural Language :: English
Classifier: Programming Language :: Python :: 3
Classifier: Programming Language :: Python :: 3.8
Classifier: Programming Language :: Python :: 3.9
Classifier: Programming Language :: Python :: 3.10
Classifier: Programming Language :: Python :: 3.11
License-File: LICENSE
License-File: AUTHORS.rst
Requires-Dist: setuptools (==62.1.0)
